VM.v
module VM (
    input clk,
    input rstn,
    input [1:0] coin_in,
    input beverage_take,
    input change_take,
    output reg [4:0] money_account,
    output reg beverage_out,
    output reg [1:0] change_out
);
    // 상태 정의
    localparam S0 = 5'd0, S1 = 5'd1, S2 = 5'd2, S3 = 5'd3, S5 = 5'd5, S6 = 5'd6, S7 = 5'd7, S8 = 5'd8, S10 = 5'd10, S11 = 5'd11, S12 = 5'd12, S15 = 5'd15, S16 = 5'd16, S20 = 5'd20;
    // 현재 상태, 다음 상태
    reg [4:0] state_now, state_next;
    reg beverage_now, beverage_next;
    reg [1:0] change_now, change_next;

    // 상태 업데이트
    always @(posedge clk or posedge rstn) begin
         // 1일때 Reset: 상태를 S0로 초기화
        if (rstn) begin
            // 초기화 현재 출력
            state_now <= S0; 
            beverage_now <= 1'b0; 
            change_now <= 2'b00; 
            // 초기화 다음 출력
            state_next <= S0; 
            beverage_next <= 1'b0; 
            change_next <= 2'b00; 
        end 
        // 클락 신호가 오면 상태 업데이트
        else begin
            state_now <= state_next;
            beverage_now <= beverage_next;
            change_now <= change_next;

            case(state_next)
                S0: begin
                    // 동전 입력 명령만 있을 경우
                    if (coin_in != 2'b00 && beverage_take == 1'b0 && change_take == 1'b0) begin
                        if (coin_in == 2'b01) begin
                            state_next <= S1;
                            beverage_next <= 1'b0;
                            change_next <= 2'b00;
                        end
                        else if (coin_in == 2'b10) begin
                            state_next <= S5;
                            beverage_next <= 1'b0;
                            change_next <= 2'b00;
                        end
                    end
                    // 그외 경우는 현재 상태 유지
                    else begin
                        state_next <= S0;
                        beverage_next <= 1'b0;
                        change_next <= 2'b00;
                    end
                end

                S1: begin
                    // 동전 입력 명령만 있을 경우
                    if (coin_in != 2'b00 && beverage_take == 1'b0 && change_take == 1'b0) begin
                        if (coin_in == 2'b01) begin 
                            state_next <= S2;
                            beverage_next <= 1'b0;
                            change_next <= 2'b00;
                        end
                        else if (coin_in == 2'b10) begin
                            state_next <= S6;
                            beverage_next <= 1'b0;
                            change_next <= 2'b00;
                        end
                    end
                    // 잔돈반환 명령만 있을 경우
                    else if (coin_in == 2'b00 && beverage_take == 1'b0 && change_take == 1'b1) begin
                        state_next <= S0;
                        change_next <= 2'b01;
                    end
                    // 그외 경우는 현재 상태 유지
                    else begin
                        state_next <= S1;
                        beverage_next <= 1'b0;
                        change_next <= 2'b00;
                    end
                end

                S2: begin
                    // 동전 입력 명령만 있을 경우
                    if (coin_in != 2'b00 && beverage_take == 1'b0 && change_take == 1'b0) begin
                        if (coin_in == 2'b01) begin
                            state_next <= S3;
                            beverage_next <= 1'b0;
                            change_next <= 2'b00;
                        end
                        else if (coin_in == 2'b10) begin
                            state_next <= S7;
                            beverage_next <= 1'b0;
                            change_next <= 2'b00;
                        end
                    end
                    // 잔돈반환 명령만 있을 경우
                    else if (coin_in == 2'b00 && beverage_take == 1'b0 && change_take == 1'b1) begin
                        state_next <= S1;
                        change_next <= 2'b01;
                    end
                    // 그외 경우는 현재 상태 유지
                    else begin
                        state_next <= S2;
                        beverage_next <= 1'b0;
                        change_next <= 2'b00;
                    end
                end

                S5: begin
                    // 동전 입력 명령만 있을 경우
                    if (coin_in != 2'b00 && beverage_take == 1'b0 && change_take == 1'b0) begin
                        if (coin_in == 2'b01) begin
                            state_next <= S6;
                            beverage_next <= 1'b0;
                            change_next <= 2'b00;
                        end
                        else if (coin_in == 2'b10) begin
                            state_next <= S10;
                            beverage_next <= 1'b0;
                            change_next <= 2'b00;
                        end
                    end
                    // 잔돈반환 명령만 있을 경우
                    else if (coin_in == 2'b00 && beverage_take == 1'b0 && change_take == 1'b1) begin
                        state_next <= S0;
                        change_next <= 2'b10;
                    end
                    // 그외 경우는 현재 상태 유지
                    else begin
                        state_next <= S5;
                        beverage_next <= 1'b0;
                        change_next <= 2'b00;
                    end
                end

                S7: begin
                    // 동전 입력 명령만 있을 경우
                    if (coin_in != 2'b00 && beverage_take == 1'b0 && change_take == 1'b0) begin
                        if (coin_in == 2'b01) begin
                            state_next <= S8;
                            beverage_next <= 1'b0;
                            change_next <= 2'b00;
                        end
                        else if (coin_in == 2'b10) begin
                            state_next <= S12;
                            beverage_next <= 1'b0;
                            change_next <= 2'b00;
                        end
                    end
                    // 잔돈반환 명령만 있을 경우
                    else if (coin_in == 2'b00 && beverage_take == 1'b0 && change_take == 1'b1) begin
                        state_next <= S2;
                        change_next <= 2'b10;
                    end
                    // 그외 경우는 현재 상태 유지
                    else begin
                        state_next <= S7;
                        beverage_next <= 1'b0;
                        change_next <= 2'b00;
                    end
                end

                S10: begin
                    // 동전 입력 명령만 있을 경우
                    if (coin_in != 2'b00 && beverage_take == 1'b0 && change_take == 1'b0) begin
                        if (coin_in == 2'b01) begin
                            state_next <= S11;
                            beverage_next <= 1'b0;
                            change_next <= 2'b00;
                        end
                        else if (coin_in == 2'b10) begin
                            state_next <= S15;
                            beverage_next <= 1'b0;
                            change_next <= 2'b00;
                        end
                    end
                    // 음료뽑기 명령만 있을 경우
                    else if (coin_in == 2'b00 && beverage_take == 1'b1 && change_take == 1'b0) begin
                        state_next <= S0;
                        beverage_next <= 1'b1;
                        change_next <= 2'b00;
                    end
                    // 잔돈반환 명령만 있을 경우    
                    else if (coin_in == 2'b00 && beverage_take == 1'b0 && change_take == 1'b1) begin
                        state_next <= S5;
                        beverage_next <= 1'b0;
                        change_next <= 2'b10;
                    end
                    // 그외 경우는 현재 상태 유지
                    else begin
                        state_next <= S10;
                        beverage_next <= 1'b0;
                        change_next <= 2'b00;
                    end
                end

                S15: begin
                    // 동전 입력 명령만 있을 경우
                    if (coin_in != 2'b00 && beverage_take == 1'b0 && change_take == 1'b0) begin
                        if (coin_in == 2'b01) begin
                            state_next <= S16;
                            beverage_next <= 1'b0;
                            change_next <= 2'b00;
                        end
                        else if (coin_in == 2'b10) begin
                            state_next <= S20;
                            beverage_next <= 1'b0;
                            change_next <= 2'b00;
                        end
                    end
                    // 음료뽑기 명령만 있을 경우
                    else if (coin_in == 2'b00 && beverage_take == 1'b1 && change_take == 1'b0) begin
                        state_next <= S5;
                        beverage_next <= 1'b1;
                        change_next <= 2'b00;
                    end
                    // 잔돈반환 명령만 있을 경우
                    else if (coin_in == 2'b00 && beverage_take == 1'b0 && change_take == 1'b1) begin
                        state_next <= S10;
                        beverage_next <= 1'b0;
                        change_next <= 2'b10;
                    end
                    // 그외 경우는 현재 상태 유지
                    else begin
                        state_next <= S15;
                        beverage_next <= 1'b0;
                        change_next <= 2'b00;
                    end
                end

                S20: begin
                    // 동전 입력 명령만 있을 경우
                    if (coin_in != 2'b00 && beverage_take == 1'b0 && change_take == 1'b0) begin
                        if (coin_in == 2'b01) begin
                            state_next <= S20;
                            beverage_next <= 1'b0;
                            change_next <= 2'b01;
                        end
                        else if (coin_in == 2'b10) begin
                            state_next <= S20;
                            beverage_next <= 1'b0;
                            change_next <= 2'b10;
                        end
                    end
                    // 음료뽑기 명령만 있을 경우
                    else if (coin_in == 2'b00 && beverage_take == 1'b1 && change_take == 1'b0) begin
                        state_next <= S10;
                        beverage_next <= 1'b1;
                        change_next <= 2'b00;
                    end
                    // 잔돈반환 명령만 있을 경우
                    else if (coin_in == 2'b00 && beverage_take == 1'b0 && change_take == 1'b1) begin
                        state_next <= S15;
                        beverage_next <= 1'b0;
                        change_next <= 2'b10;
                    end
                    // 그외 경우는 현재 상태 유지
                    else begin
                        state_next <= S20;
                        beverage_next <= 1'b0;
                        change_next <= 2'b00;
                    end
                end     
            endcase
        end
    end

    // 출력 업데이트
    always @(state_now or beverage_now or change_now) begin
        case(state_now)
            S0: money_account <= 5'd0;
            S1: money_account <= 5'd1;
            S2: money_account <= 5'd2;
            S5: money_account <= 5'd5;
            S7: money_account <= 5'd7;
            S10: money_account <= 5'd10;
            S15: money_account <= 5'd15;
            S20: money_account <= 5'd20;
        endcase
        case (beverage_now)
            1'b0: beverage_out <= 1'b0;
            1'b1: beverage_out <= 1'b1;
        endcase
        case (change_now)
            2'b00: change_out <= 2'b00;
            2'b01: change_out <= 2'b01;
            2'b10: change_out <= 2'b10;
        endcase
    end

endmodule

VM_tb.v
`timescale 1ns / 1ps

module VM_tb;

    reg clk;
    reg rstn;
    reg beverage_take;
    reg change_take;
    reg [1:0] coin_in;
    wire beverage_out;
    wire [1:0] change_out;
    wire [4:0] money_account;

    VM u_vm (
        .clk(clk),
        .rstn(rstn),
        .beverage_take(beverage_take),
        .change_take(change_take),
        .coin_in(coin_in),
        .beverage_out(beverage_out),
        .change_out(change_out),
        .money_account(money_account)
    );

    always #5 clk = ~clk;

    initial begin
        // 초기화
        clk = 0; rstn = 1; 

        // 동시입력이 무시되는지 모든 경우 테스트
        #5 rstn = 0; coin_in = 2'b01; beverage_take = 1'b1; change_take = 1'b1; // 모든 명령 동시 입력(1000원 동전입력)
        #10 rstn = 0; coin_in = 2'b01; beverage_take = 1'b1; change_take = 1'b0; // 1000원 동전입력, 음료뽑기 명령 동시 입력
        #10 rstn = 0; coin_in = 2'b01; beverage_take = 1'b0; change_take = 1'b1; // 1000원 동전입력, 잔돈반환 명령 동시 입력
        #10 rstn = 0; coin_in = 2'b10; beverage_take = 1'b1; change_take = 1'b1; // 모든 명령 동시 입력(5000원 동전입력)
        #10 rstn = 0; coin_in = 2'b10; beverage_take = 1'b1; change_take = 1'b0; // 5000원 동전입력, 음료뽑기 명령 동시 입력
        #10 rstn = 0; coin_in = 2'b10; beverage_take = 1'b0; change_take = 1'b1; // 5000원 동전입력, 잔돈반환 명령 동시 입력
        #10 rstn = 0; coin_in = 2'b00; beverage_take = 1'b1; change_take = 1'b1; // 음료뽑기 명령, 잔돈반환 명령 동시 입력

        // 돈 20000원 채우기 (5000원으로 4번)
        #10 rstn = 0; coin_in = 2'b10; beverage_take = 1'b0; change_take = 1'b0; // 5000원 동전입력 
        #10 rstn = 0; coin_in = 2'b10; beverage_take = 1'b0; change_take = 1'b0; // 5000원 동전입력
        #10 rstn = 0; coin_in = 2'b10; beverage_take = 1'b0; change_take = 1'b0; // 5000원 동전입력 
        #10 rstn = 0; coin_in = 2'b10; beverage_take = 1'b0; change_take = 1'b0; // 5000원 동전입력
        
        // 추가로 돈을 넣어 초과된 돈을 반환하는지 확인
        #10 rstn = 0; coin_in = 2'b01; beverage_take = 1'b0; change_take = 1'b0; // 1000원 동전입력
        
        // 음료 두번 출력
        #10 rstn = 0; coin_in = 2'b00; beverage_take = 1'b1; change_take = 1'b0; // 음료뽑기 명령
        #10 rstn = 0; coin_in = 2'b00; beverage_take = 1'b1; change_take = 1'b0; // 음료뽑기 명령
        
        // 7000원 동전 넣기
        #10 rstn = 0; coin_in = 2'b01; beverage_take = 1'b0; change_take = 1'b0; // 1000원 동전입력
        #10 rstn = 0; coin_in = 2'b01; beverage_take = 1'b0; change_take = 1'b0; // 1000원 동전입력
        #10 rstn = 0; coin_in = 2'b10; beverage_take = 1'b0; change_take = 1'b0; // 5000원 동전입력
        
        // 음료뽑기
        #10 rstn = 0; coin_in = 2'b00; beverage_take = 1'b1; change_take = 1'b0;
        
        // 잔돈 반환
        #10 rstn = 0; coin_in = 2'b00; beverage_take = 1'b0; change_take = 1'b1; // 5000원 반환
        #10 rstn = 0; coin_in = 2'b00; beverage_take = 1'b0; change_take = 1'b1; // 1000원 반환
        #10 rstn = 0; coin_in = 2'b00; beverage_take = 1'b0; change_take = 1'b1; // 1000원 반환 -> 잔돈 모두 반환 완료

        #10 rstn = 0; coin_in = 2'b00; beverage_take = 1'b0; change_take = 1'b0; // 종료
        
        // 출력이 모두 확인될 때까지 기다리고 나서 종료
        #20 $finish;
    end

    initial begin
        $dumpfile("VM.vcd");
        $dumpvars(0, VM_tb);
    end
endmodule

VM.vcd
$date
	Sat Jun  7 02:32:41 2025
$end
$version
	Icarus Verilog
$end
$timescale
	1ps
$end
$scope module VM_tb $end
$var wire 5 ! money_account [4:0] $end
$var wire 2 " change_out [1:0] $end
$var wire 1 # beverage_out $end
$var reg 1 $ beverage_take $end
$var reg 1 % change_take $end
$var reg 1 & clk $end
$var reg 2 ' coin_in [1:0] $end
$var reg 1 ( rstn $end
$scope module u_vm $end
$var wire 1 $ beverage_take $end
$var wire 1 % change_take $end
$var wire 1 & clk $end
$var wire 2 ) coin_in [1:0] $end
$var wire 1 ( rstn $end
$var parameter 5 * S0 $end
$var parameter 5 + S1 $end
$var parameter 5 , S10 $end
$var parameter 5 - S11 $end
$var parameter 5 . S12 $end
$var parameter 5 / S15 $end
$var parameter 5 0 S16 $end
$var parameter 5 1 S2 $end
$var parameter 5 2 S20 $end
$var parameter 5 3 S3 $end
$var parameter 5 4 S5 $end
$var parameter 5 5 S6 $end
$var parameter 5 6 S7 $end
$var parameter 5 7 S8 $end
$var reg 1 8 beverage_next $end
$var reg 1 9 beverage_now $end
$var reg 1 # beverage_out $end
$var reg 2 : change_next [1:0] $end
$var reg 2 ; change_now [1:0] $end
$var reg 2 < change_out [1:0] $end
$var reg 5 = money_account [4:0] $end
$var reg 5 > state_next [4:0] $end
$var reg 5 ? state_now [4:0] $end
$upscope $end
$upscope $end
$enddefinitions $end
$comment Show the parameter values. $end
$dumpall
b1000 7
b111 6
b110 5
b101 4
b11 3
b10100 2
b10 1
b10000 0
b1111 /
b1100 .
b1011 -
b1010 ,
b1 +
b0 *
$end
#0
$dumpvars
b0 ?
b0 >
b0 =
b0 <
b0 ;
b0 :
09
08
bx )
1(
bx '
0&
x%
x$
0#
b0 "
b0 !
$end
#5000
1%
1$
b1 '
b1 )
0(
1&
#10000
0&
#15000
1&
0%
#20000
0&
#25000
1&
1%
0$
#30000
0&
#35000
1&
1$
b10 '
b10 )
#40000
0&
#45000
1&
0%
#50000
0&
#55000
1&
1%
0$
#60000
0&
#65000
1&
1$
b0 '
b0 )
#70000
0&
#75000
b101 >
1&
0%
0$
b10 '
b10 )
#80000
0&
#85000
b101 !
b101 =
b1010 >
b101 ?
1&
#90000
0&
#95000
b1010 !
b1010 =
b1111 >
b1010 ?
1&
#100000
0&
#105000
b1111 !
b1111 =
b10100 >
b1111 ?
1&
#110000
0&
#115000
b10100 !
b10100 =
b1 :
b10100 ?
1&
b1 '
b1 )
#120000
0&
#125000
b1 "
b1 <
b0 :
18
b1010 >
b1 ;
1&
1$
b0 '
b0 )
#130000
0&
#135000
b0 "
b0 <
1#
b1010 !
b1010 =
b0 >
b0 ;
19
b1010 ?
1&
#140000
0&
#145000
b0 !
b0 =
08
b1 >
b0 ?
1&
0$
b1 '
b1 )
#150000
0&
#155000
0#
b1 !
b1 =
b10 >
09
b1 ?
1&
#160000
0&
#165000
b10 !
b10 =
b111 >
b10 ?
1&
b10 '
b10 )
#170000
0&
#175000
b111 !
b111 =
b111 ?
1&
1$
b0 '
b0 )
#180000
0&
#185000
b10 :
b10 >
1&
1%
0$
#190000
0&
#195000
b10 "
b10 <
b10 !
b10 =
b1 :
b1 >
b10 ;
b10 ?
1&
#200000
0&
#205000
b1 "
b1 <
b1 !
b1 =
b0 >
b1 ;
b1 ?
1&
#210000
0&
#215000
b0 !
b0 =
b0 :
b0 ?
1&
0%
#220000
0&
#225000
b0 "
b0 <
b0 ;
1&
